odoo/addons/l10n_be_cooperator_portal/README.rst
odoo/addons/l10n_be_cooperator_portal/__init__.py
odoo/addons/l10n_be_cooperator_portal/__manifest__.py
odoo/addons/l10n_be_cooperator_portal/controllers/__init__.py
odoo/addons/l10n_be_cooperator_portal/controllers/main.py
odoo/addons/l10n_be_cooperator_portal/i18n/fr_BE.po
odoo/addons/l10n_be_cooperator_portal/i18n/l10n_be_cooperator_portal.pot
odoo/addons/l10n_be_cooperator_portal/readme/CONTRIBUTORS.rst
odoo/addons/l10n_be_cooperator_portal/readme/DESCRIPTION.rst
odoo/addons/l10n_be_cooperator_portal/static/description/icon.png
odoo/addons/l10n_be_cooperator_portal/static/description/index.html
odoo/addons/l10n_be_cooperator_portal/views/portal_templates.xml
odoo12_addon_l10n_be_cooperator_portal-12.0.1.1.1.dist-info/METADATA
odoo12_addon_l10n_be_cooperator_portal-12.0.1.1.1.dist-info/WHEEL
odoo12_addon_l10n_be_cooperator_portal-12.0.1.1.1.dist-info/top_level.txt
odoo12_addon_l10n_be_cooperator_portal-12.0.1.1.1.dist-info/RECORD
