Metadata-Version: 2.1
Name: odoo12-addon-l10n-be-cooperator-portal
Version: 12.0.1.1.1
Summary: Give access to Tax Shelter Report in the portal.
Home-page: https://github.com/OCA/cooperative
Author: Coop IT Easy SC, Odoo Community Association (OCA)
Author-email: support@odoo-community.org
License: AGPL-3
Platform: UNKNOWN
Classifier: Programming Language :: Python
Classifier: Framework :: Odoo
Classifier: Framework :: Odoo :: 12.0
Classifier: License :: OSI Approved :: GNU Affero General Public License v3
Requires-Python: >=3.5
Requires-Dist: odoo12-addon-l10n-be-cooperator
Requires-Dist: odoo (<12.1dev,>=12.0a)
